dans_log_formatter/__init__.py
dans_log_formatter/contrib/__init__.py
dans_log_formatter/contrib/celery/__init__.py
dans_log_formatter/contrib/celery/provider.py
dans_log_formatter/contrib/django/__init__.py
dans_log_formatter/contrib/django/middleware.py
dans_log_formatter/contrib/django/provider.py
dans_log_formatter/contrib/fastapi/__init__.py
dans_log_formatter/contrib/fastapi/middleware.py
dans_log_formatter/contrib/fastapi/provider.py
dans_log_formatter/contrib/flask/__init__.py
dans_log_formatter/contrib/flask/provider.py
dans_log_formatter/contrib/orjson.py
dans_log_formatter/contrib/ujson.py
dans_log_formatter/formatter.py
dans_log_formatter/formatter_error.py
dans_log_formatter/providers/__init__.py
dans_log_formatter/providers/abstract.py
dans_log_formatter/providers/abstract_context.py
dans_log_formatter/providers/context.py
dans_log_formatter/providers/extra.py
dans_log_formatter/providers/runtime.py
dans_log_formatter-0.2.0.dist-info/LICENSE
dans_log_formatter-0.2.0.dist-info/METADATA
dans_log_formatter-0.2.0.dist-info/WHEEL
dans_log_formatter-0.2.0.dist-info/RECORD
