Metadata-Version: 2.3
Name: dans-log-formatter
Version: 0.2.0
Summary: A simple, extendable log formatter for Python
Author: danyi1212
Author-email: danyi1212@gmail.com
Requires-Python: >=3.9,<4.0
Classifier: Programming Language :: Python :: 3
Classifier: Programming Language :: Python :: 3.9
Classifier: Programming Language :: Python :: 3.10
Classifier: Programming Language :: Python :: 3.11
Classifier: Programming Language :: Python :: 3.12
Classifier: Programming Language :: Python :: 3.13
Provides-Extra: celery
Provides-Extra: django
Provides-Extra: fastapi
Provides-Extra: flask
Provides-Extra: orjson
Provides-Extra: ujson
Requires-Dist: celery ; extra == "celery"
Requires-Dist: django ; extra == "django"
Requires-Dist: fastapi ; extra == "fastapi"
Requires-Dist: flask ; extra == "flask"
Requires-Dist: orjson ; extra == "orjson"
Requires-Dist: ujson ; extra == "ujson"
